{"timestamp": "2020-01-01T00:00:00Z", "regime": "TRENDING", "signal_source": "DONCHIAN_BREAKOUT", "reversal_blocker_result": "PASSED", "xgboost_probability": 0.73, "timeframe_scores": {"1H": 1, "4H": 1, "Daily": 1}, "timeframe_total_score": 3, "position_size_usd": 1000.0, "position_size_btc": 0.01, "entry_price": 80000.0, "stop_loss_level": 79250.0, "take_profit_level": null, "exit_price": 81250.0, "exit_reason": "TRAILING_STOP", "pnl_usd_gross": 100.0, "pnl_usd_net": 90.0, "pnl_pct": 1.56, "fees_paid_usd": 10.0, "portfolio_value_after": 1000090.0, "drawdown_at_trade_pct": 0.0, "cooldown_triggered": true, "partial_fill": false, "partial_fill_pct": null}
